gns3fy_next/__init__.py
gns3fy_next/drawing_utils.py
gns3fy_next/gns3fy.py
gns3fy_next-1.0.0.dist-info/METADATA
gns3fy_next-1.0.0.dist-info/WHEEL
gns3fy_next-1.0.0.dist-info/RECORD
