Metadata-Version: 2.4
Name: gns3fy-next
Version: 1.0.0
Summary: Python wrapper around GNS3 Server API v2 and v3
License: MIT
Keywords: network,gns3,python,restapi,netdev
Author: Guobin Yue
Author-email: guobinyue.gb@gmail.com
Requires-Python: >=3.10,<4.0
Classifier: License :: OSI Approved :: MIT License
Classifier: Programming Language :: Python :: 3
Classifier: Programming Language :: Python :: 3.10
Classifier: Programming Language :: Python :: 3.11
Classifier: Programming Language :: Python :: 3.12
Classifier: Programming Language :: Python :: 3.13
Classifier: Programming Language :: Python :: 3.14
Requires-Dist: pydantic (>=2.0,<3.0)
Requires-Dist: pyjwt (>=2.0,<3.0)
Requires-Dist: requests (>=2.22,<3.0)
Requires-Dist: urllib3 (>=1.26,<2.0)
Project-URL: Homepage, https://github.com/yueguobin/gns3fy-next
Project-URL: Repository, https://github.com/yueguobin/gns3fy-next
